MANIFEST.in
README.txt
development.ini
receive.py
sender.py
server.ini
setup.cfg
setup.py
start-stop-sms.sh
test.ini
web.ini
SMSShell.egg-info/PKG-INFO
SMSShell.egg-info/SOURCES.txt
SMSShell.egg-info/dependency_links.txt
SMSShell.egg-info/entry_points.txt
SMSShell.egg-info/paste_deploy_config.ini_tmpl
SMSShell.egg-info/paster_plugins.txt
SMSShell.egg-info/requires.txt
SMSShell.egg-info/top_level.txt
apache-www/index.html
apache-www/index.shtml
apache-www/web.ini
apache-www/cgi-bin/smsshell.cgi
docs/index.txt
etc-kannel/dlr-mysql.conf
etc-kannel/kannel.conf
etc-kannel/modems.conf
etc-kannel/services.conf
etc-kannel/smsblaster.conf
etc-kannel/smsshell.conf
etc-smsshell/custom.ini
smsshell/__init__.py
smsshell/screen.rc
smsshell/websetup.py
smsshell/config/__init__.py
smsshell/config/environment.py
smsshell/config/ini-stuff.ini
smsshell/config/middleware.py
smsshell/config/routing.py
smsshell/config/test.py
smsshell/controllers/__init__.py
smsshell/controllers/admin.py
smsshell/controllers/archive.py
smsshell/controllers/contact.py
smsshell/controllers/custom.py
smsshell/controllers/error.py
smsshell/controllers/estate.py
smsshell/controllers/filter.py
smsshell/controllers/folder.py
smsshell/controllers/inbox.py
smsshell/controllers/label.py
smsshell/controllers/message.py
smsshell/controllers/outbox.py
smsshell/controllers/response.py
smsshell/controllers/sent.py
smsshell/controllers/template.py
smsshell/lib/__init__.py
smsshell/lib/app_globals.py
smsshell/lib/base.py
smsshell/lib/helpers.py
smsshell/model/__init__.py
smsshell/public/index.html
smsshell/public/old_index.html
smsshell/public/smsshell.css
smsshell/public/icons/delete.png
smsshell/public/icons/details.png
smsshell/public/icons/edit.png
smsshell/public/icons/first.png
smsshell/public/icons/last.png
smsshell/public/icons/new.png
smsshell/public/icons/next.png
smsshell/public/icons/prev.png
smsshell/public/icons/reply.png
smsshell/public/icons/crystal_clear/add.png
smsshell/public/icons/crystal_clear/back.png
smsshell/public/icons/crystal_clear/cut.png
smsshell/public/icons/crystal_clear/delete.png
smsshell/public/icons/crystal_clear/edit.png
smsshell/public/icons/crystal_clear/first.png
smsshell/public/icons/crystal_clear/forward.png
smsshell/public/icons/crystal_clear/info.png
