Metadata-Version: 1.0
Name: SMSShell
Version: 0.1.1dev-r196
Summary: SMSShell Web Interface to modify SMSShell Component
Home-page: UNKNOWN
Author: Emanuel Gardaya Calso
Author-email: egcalso@gmail.com
License: UNKNOWN
Platform: UNKNOWN
